simplecloudfunlocaltest/__init__.py
simplecloudfunlocaltest/_cli.py
simplecloudfunlocaltest/simplefunctions.py
simplecloudfunlocaltest-0.1.0.dist-info/LICENSE.txt
simplecloudfunlocaltest-0.1.0.dist-info/METADATA
simplecloudfunlocaltest-0.1.0.dist-info/WHEEL
simplecloudfunlocaltest-0.1.0.dist-info/entry_points.txt
simplecloudfunlocaltest-0.1.0.dist-info/top_level.txt
simplecloudfunlocaltest-0.1.0.dist-info/RECORD
