Metadata-Version: 2.1
Name: simplecloudfunlocaltest
Version: 0.1.0
Summary: Funcion para explicar en el data hub
Home-page: UNKNOWN
Author: Marco Ycaza
Author-email: UNKNOWN
License: MIT
Platform: UNKNOWN
Requires-Dist: flask
Requires-Dist: google-cloud
